[
  {
    "epoch": 1,
    "loss": 1.094915,
    "miou": 0.5059
  },
  {
    "epoch": 2,
    "loss": 1.006772,
    "miou": 0.5168
  },
  {
    "epoch": 3,
    "loss": 0.912527,
    "miou": 0.5206
  },
  {
    "epoch": 4,
    "loss": 0.834409,
    "miou": 0.536
  },
  {
    "epoch": 5,
    "loss": 0.768388,
    "miou": 0.5422
  },
  {
    "epoch": 6,
    "loss": 0.698041,
    "miou": 0.5538
  },
  {
    "epoch": 7,
    "loss": 0.630785,
    "miou": 0.5666
  },
  {
    "epoch": 8,
    "loss": 0.584678,
    "miou": 0.5697
  },
  {
    "epoch": 9,
    "loss": 0.534166,
    "miou": 0.5822
  },
  {
    "epoch": 10,
    "loss": 0.484028,
    "miou": 0.5876
  },
  {
    "epoch": 11,
    "loss": 0.447377,
    "miou": 0.5961
  },
  {
    "epoch": 12,
    "loss": 0.413893,
    "miou": 0.6019
  },
  {
    "epoch": 13,
    "loss": 0.376638,
    "miou": 0.6124
  },
  {
    "epoch": 14,
    "loss": 0.339542,
    "miou": 0.6251
  },
  {
    "epoch": 15,
    "loss": 0.308496,
    "miou": 0.6292
  },
  {
    "epoch": 16,
    "loss": 0.282008,
    "miou": 0.6411
  },
  {
    "epoch": 17,
    "loss": 0.270753,
    "miou": 0.64
  },
  {
    "epoch": 18,
    "loss": 0.2416,
    "miou": 0.6601
  },
  {
    "epoch": 19,
    "loss": 0.217163,
    "miou": 0.6695
  },
  {
    "epoch": 20,
    "loss": 0.193149,
    "miou": 0.6757
  },
  {
    "epoch": 21,
    "loss": 0.184848,
    "miou": 0.6831
  },
  {
    "epoch": 22,
    "loss": 0.166673,
    "miou": 0.6883
  },
  {
    "epoch": 23,
    "loss": 0.148062,
    "miou": 0.6967
  },
  {
    "epoch": 24,
    "loss": 0.140949,
    "miou": 0.7087
  },
  {
    "epoch": 25,
    "loss": 0.1196,
    "miou": 0.7148
  },
  {
    "epoch": 26,
    "loss": 0.113739,
    "miou": 0.7238
  },
  {
    "epoch": 27,
    "loss": 0.105881,
    "miou": 0.7431
  },
  {
    "epoch": 28,
    "loss": 0.096407,
    "miou": 0.7413
  },
  {
    "epoch": 29,
    "loss": 0.089999,
    "miou": 0.7472
  },
  {
    "epoch": 30,
    "loss": 0.089583,
    "miou": 0.7595
  },
  {
    "epoch": 31,
    "loss": 0.072943,
    "miou": 0.7545
  },
  {
    "epoch": 32,
    "loss": 0.065656,
    "miou": 0.77
  },
  {
    "epoch": 33,
    "loss": 0.058416,
    "miou": 0.784
  },
  {
    "epoch": 34,
    "loss": 0.055664,
    "miou": 0.786
  },
  {
    "epoch": 35,
    "loss": 0.054902,
    "miou": 0.8035
  },
  {
    "epoch": 36,
    "loss": 0.054519,
    "miou": 0.8168
  },
  {
    "epoch": 37,
    "loss": 0.04628,
    "miou": 0.8184
  },
  {
    "epoch": 38,
    "loss": 0.034111,
    "miou": 0.8287
  },
  {
    "epoch": 39,
    "loss": 0.045265,
    "miou": 0.8362
  },
  {
    "epoch": 40,
    "loss": 0.031985,
    "miou": 0.8503
  },
  {
    "epoch": 41,
    "loss": 0.01879,
    "miou": 0.8458
  },
  {
    "epoch": 42,
    "loss": 0.026349,
    "miou": 0.8685
  },
  {
    "epoch": 43,
    "loss": 0.017706,
    "miou": 0.8675
  },
  {
    "epoch": 44,
    "loss": 0.017482,
    "miou": 0.8781
  },
  {
    "epoch": 45,
    "loss": 0.01652,
    "miou": 0.8873
  },
  {
    "epoch": 46,
    "loss": 0.017095,
    "miou": 0.8881
  },
  {
    "epoch": 47,
    "loss": 0.011743,
    "miou": 0.9123
  },
  {
    "epoch": 48,
    "loss": 0.013816,
    "miou": 0.9041
  },
  {
    "epoch": 49,
    "loss": 0.014116,
    "miou": 0.9228
  },
  {
    "epoch": 50,
    "loss": 0.008,
    "miou": 0.9294
  }
]